keboola_streamlit/__init__.py
keboola_streamlit/keboola_streamlit.py
keboola_streamlit-0.1.3.dist-info/licenses/LICENSE
keboola_streamlit-0.1.3.dist-info/METADATA
keboola_streamlit-0.1.3.dist-info/WHEEL
keboola_streamlit-0.1.3.dist-info/top_level.txt
keboola_streamlit-0.1.3.dist-info/RECORD
