Metadata-Version: 2.4
Name: keboola_streamlit
Version: 0.1.3
Summary: A Python library that simplifies Keboola SAPI integration in Streamlit apps.
Author-email: pandyandy <andrea.novakova@keboola.com>, yustme <vojta.tuma@keboola.com>
License: MIT License
Project-URL: Repository, https://github.com/keboola/keboola_streamlit/
Classifier: Programming Language :: Python :: 3
Classifier: License :: OSI Approved :: MIT License
Classifier: Operating System :: OS Independent
Classifier: Intended Audience :: Developers
Classifier: Topic :: Software Development :: Libraries :: Python Modules
Requires-Python: >=3.7
License-File: LICENSE
Requires-Dist: streamlit>=1.37.0
Requires-Dist: pandas
Requires-Dist: kbcstorage
Requires-Dist: deprecated
Requires-Dist: snowflake-snowpark-python
Dynamic: license-file
